pytest_dashboard/__init__.py
pytest_dashboard/conftest.py
pytest_dashboard-2.0.0.dist-info/LICENSE
pytest_dashboard-2.0.0.dist-info/METADATA
pytest_dashboard-2.0.0.dist-info/WHEEL
pytest_dashboard-2.0.0.dist-info/entry_points.txt
pytest_dashboard-2.0.0.dist-info/RECORD
