Metadata-Version: 2.3
Name: pytest-dashboard
Version: 2.0.0
Summary: 
License: BSD-3-Clause
Author: kazuma.naito
Author-email: kazuma.naito@murata.com
Requires-Python: >=3.9,<4.0.0
Classifier: License :: OSI Approved :: BSD License
Classifier: Programming Language :: Python :: 3
Classifier: Programming Language :: Python :: 3.9
Classifier: Programming Language :: Python :: 3.10
Classifier: Programming Language :: Python :: 3.11
Classifier: Programming Language :: Python :: 3.12
Classifier: Programming Language :: Python :: 3.13
Requires-Dist: fire (>=0.7.0)
Requires-Dist: pytest (>=7.4.3,<8.0.0)
Requires-Dist: pyyaml (>=6.0.1,<7.0.0)
Project-URL: Repository, https://github.com/pyfemtet/pytest-dashboard
